my_retry/retry_model.py
my_retry-0.2.0.dist-info/METADATA
my_retry-0.2.0.dist-info/WHEEL
my_retry-0.2.0.dist-info/license.txt
my_retry-0.2.0.dist-info/top_level.txt
my_retry-0.2.0.dist-info/zip-safe
my_retry-0.2.0.dist-info/RECORD
