Metadata-Version: 2.1
Name: my-retry
Version: 0.2.0
Summary: Retry module, You can choose to raise error or return the specified parameters
Home-page: https://gitee.com/yternal/my-retry
Author: yrq
Author-email: 1307272972@qq.com
License: MIT
License-File: license.txt
Requires-Dist: loguru (>=0.6.0)
